Ansary.py
EE.py
FilaliAnsary-1.0.1.dist-info/LICENSE.txt
FilaliAnsary-1.0.1.dist-info/METADATA
FilaliAnsary-1.0.1.dist-info/WHEEL
FilaliAnsary-1.0.1.dist-info/top_level.txt
FilaliAnsary-1.0.1.dist-info/RECORD
