Metadata-Version: 2.1
Name: FilaliAnsary
Version: 1.0.1
Summary: A Python package created to kill time.
Home-page: UNKNOWN
Author: Abdelouahab FILALI ANSARY
License: MIT
Platform: UNKNOWN
Classifier: License :: OSI Approved :: MIT License
Classifier: Programming Language :: Python :: 3
Classifier: Programming Language :: Python :: 3.7
Requires-Dist: requests
Provides-Extra: dev
Requires-Dist: pytest (>=3.7) ; extra == 'dev'
